orbis_plugin_storage_single_view/__init__.py
orbis_plugin_storage_single_view/html_templates.py
orbis_plugin_storage_single_view/main.py
orbis_plugin_storage_single_view-2.1.1.dist-info/LICENSE
orbis_plugin_storage_single_view-2.1.1.dist-info/METADATA
orbis_plugin_storage_single_view-2.1.1.dist-info/WHEEL
orbis_plugin_storage_single_view-2.1.1.dist-info/top_level.txt
orbis_plugin_storage_single_view-2.1.1.dist-info/RECORD
